{"status":"done","chunks":{"app":["js/app.js","app.eebef35daee6fb207c43.hot-update.js"]},"publicPath":"http://0.0.0.0:8080/","assets":{"js/app.js":{"name":"js/app.js","path":"C:\\Users\\asus\\Documents\\Project\\vue\\chatapp\\vue-chat-app\\frontend\\dist\\js\\app.js","publicPath":"http://0.0.0.0:8080/js/app.js"},"app.eebef35daee6fb207c43.hot-update.js":{"name":"app.eebef35daee6fb207c43.hot-update.js","path":"C:\\Users\\asus\\Documents\\Project\\vue\\chatapp\\vue-chat-app\\frontend\\dist\\app.eebef35daee6fb207c43.hot-update.js","publicPath":"http://0.0.0.0:8080/app.eebef35daee6fb207c43.hot-update.js"},"eebef35daee6fb207c43.hot-update.json":{"name":"eebef35daee6fb207c43.hot-update.json","path":"C:\\Users\\asus\\Documents\\Project\\vue\\chatapp\\vue-chat-app\\frontend\\dist\\eebef35daee6fb207c43.hot-update.json","publicPath":"http://0.0.0.0:8080/eebef35daee6fb207c43.hot-update.json"},"index.html":{"name":"index.html","path":"C:\\Users\\asus\\Documents\\Project\\vue\\chatapp\\vue-chat-app\\frontend\\dist\\index.html","publicPath":"http://0.0.0.0:8080/index.html"}}}